fastapi_lambda/__init__.py
fastapi_lambda/_compat.py
fastapi_lambda/app.py
fastapi_lambda/dependencies.py
fastapi_lambda/exceptions.py
fastapi_lambda/middleware/__init__.py
fastapi_lambda/middleware/cors.py
fastapi_lambda/openapi_schema.py
fastapi_lambda/param_functions.py
fastapi_lambda/params.py
fastapi_lambda/py.typed
fastapi_lambda/request.py
fastapi_lambda/response.py
fastapi_lambda/router.py
fastapi_lambda/security.py
fastapi_lambda/types.py
fastapi_lambda/utils.py
fastapi_lambda-0.2.1.dist-info/METADATA
fastapi_lambda-0.2.1.dist-info/WHEEL
fastapi_lambda-0.2.1.dist-info/licenses/LICENSE
fastapi_lambda-0.2.1.dist-info/licenses/NOTICE
fastapi_lambda-0.2.1.dist-info/RECORD
