Metadata-Version: 2.4
Name: fastapi-lambda
Version: 0.2.1
Summary: FastAPI fork optimized for AWS Lambda with minimal cold start overhead (inspired by FastAPI by Sebastián Ramírez)
License: MIT
License-File: LICENSE
License-File: NOTICE
Keywords: fastapi,lambda,aws,serverless,api,rest,openapi,pydantic
Author: Tobias Silicani
Author-email: tobias@example.com
Requires-Python: >=3.10
Classifier: Development Status :: 4 - Beta
Classifier: Intended Audience :: Developers
Classifier: License :: OSI Approved :: MIT License
Classifier: Programming Language :: Python :: 3
Classifier: Programming Language :: Python :: 3.10
Classifier: Programming Language :: Python :: 3.11
Classifier: Programming Language :: Python :: 3.12
Classifier: Topic :: Internet :: WWW/HTTP
Classifier: Topic :: Software Development :: Libraries :: Python Modules
Classifier: Framework :: FastAPI
Requires-Dist: pydantic (>=2.7.0,<3.0.0)
Requires-Dist: typing-extensions (>=4.8.0)
Project-URL: Documentation, https://github.com/tsilicani/fastapi-lambda#readme
Project-URL: Homepage, https://github.com/tsilicani/fastapi-lambda
Project-URL: Issues, https://github.com/tsilicani/fastapi-lambda/issues
Project-URL: Repository, https://github.com/tsilicani/fastapi-lambda
